dmqtt/__init__.py
dmqtt/mosquitto.py
dmqtt/shortcuts.py
dmqtt/signals.py
dmqtt/vernemq.py
dmqtt/management/__init__.py
dmqtt/management/commands/__init__.py
dmqtt/management/commands/mqtt-test.py
dmqtt/management/commands/mqtt.py
tests/__init__.py
tests/test_mosquitto.py
tests/example/__init__.py
tests/example/__main__.py
tests/example/settings.py
tests/example/urls.py
venv/bin/activate_this.py
venv/bin/django-admin.py
django_mqtt-0.4.3.dist-info/LICENSE
django_mqtt-0.4.3.dist-info/METADATA
django_mqtt-0.4.3.dist-info/WHEEL
django_mqtt-0.4.3.dist-info/top_level.txt
django_mqtt-0.4.3.dist-info/RECORD
